{
  "awardsPoints": true,
  "categories": {
    "categories": [
      {
        "competitionCount": 94,
        "datasetCount": 150,
        "description": null,
        "displayName": "tabular data",
        "fontAwesomeIcon": null,
        "fullPath": "data type > tabular data",
        "id": 14101,
        "isInherited": false,
        "listingUrl": "/competitions?sortBy=relevance&group=all&search=tag%3A%27tabular data%27",
        "name": "tabular data",
        "scriptCount": 116,
        "tagUrl": "/tags/tabular-data",
        "totalCount": 360
      },
      {
        "competitionCount": 31,
        "datasetCount": 98,
        "description": null,
        "displayName": "binary classification",
        "fontAwesomeIcon": null,
        "fullPath": "problem type > binary classification",
        "id": 14201,
        "isInherited": false,
        "listingUrl": "/competitions?sortBy=relevance&group=all&search=tag%3A%27binary classification%27",
        "name": "binary classification",
        "scriptCount": 477,
        "tagUrl": "/tags/binary-classification",
        "totalCount": 606
      }
    ],
    "type": "competition"
  },
  "competitionDescription": "Predict if a driver will file an insurance claim next year.",
  "competitionId": 7082,
  "competitionName": "porto-seguro-safe-driver-prediction",
  "competitionTitle": "Porto Seguro\u2019s Safe Driver Prediction",
  "competitionUrl": "/c/porto-seguro-safe-driver-prediction",
  "coverImageUrl": null,
  "deadline": "2017-11-29T23:59:00Z",
  "enabledDate": "2017-09-29T16:24:29.747Z",
  "evaluationMetric": "Normalized Gini Index",
  "hostSegment": "featured",
  "hostSegmentTitle": "Featured",
  "isInClass": false,
  "isKernelsSubmissionsOnly": false,
  "isLimited": false,
  "isOngoingCompetition": false,
  "isPrivate": false,
  "maxDailySubmissions": 5,
  "maxTeamSize": null,
  "medal": null,
  "mergerDeadline": "2017-11-22T23:59:00Z",
  "newEntrantDeadline": "2017-11-22T23:59:00Z",
  "organizationAvatarUrl": null,
  "organizationName": "Porto Seguro",
  "organizationUrl": "porto-seguro",
  "rewardDisplay": "$25,000",
  "rewardQuantity": 25000.0,
  "rewardTypeName": "USD",
  "submissionsDisabled": false,
  "thumbnailImageUrl": "https://storage.googleapis.com/kaggle-competitions/kaggle/7082/logos/thumb76_76.png",
  "totalKernels": 0,
  "totalTeams": 5163,
  "userHasEntered": false,
  "userRank": null,
  "userTeamUsers": []
}
