{
  "awardsPoints": true,
  "categories": {
    "categories": [
      {
        "competitionCount": 94,
        "datasetCount": 150,
        "description": null,
        "displayName": "tabular data",
        "fontAwesomeIcon": null,
        "fullPath": "data type > tabular data",
        "id": 14101,
        "isInherited": false,
        "listingUrl": "/competitions?sortBy=relevance&group=all&search=tag%3A%27tabular data%27",
        "name": "tabular data",
        "scriptCount": 116,
        "tagUrl": "/tags/tabular-data",
        "totalCount": 360
      },
      {
        "competitionCount": 5,
        "datasetCount": 204,
        "description": "Time series analysis is the 4th dimension of data analysis. Our human minds can't visualize time but thankfully there are some really great plotting libraries out there to fix that problem.",
        "displayName": "time series",
        "fontAwesomeIcon": null,
        "fullPath": "mathematics and logic > statistics > time series",
        "id": 6618,
        "isInherited": false,
        "listingUrl": "/competitions?sortBy=relevance&group=all&search=tag%3A%27time series%27",
        "name": "time series",
        "scriptCount": 403,
        "tagUrl": "/tags/time-series",
        "totalCount": 612
      },
      {
        "competitionCount": 15,
        "datasetCount": 1732,
        "description": "An interconnected network of tubes that connects the entire world together. This tag covers a broad range of tags; anything from cryptocurrency to website analytics.",
        "displayName": "internet",
        "fontAwesomeIcon": null,
        "fullPath": "technology and applied sciences > computing > internet",
        "id": 12116,
        "isInherited": false,
        "listingUrl": "/competitions?sortBy=relevance&group=all&search=tag%3A%27internet%27",
        "name": "internet",
        "scriptCount": 181,
        "tagUrl": "/tags/internet",
        "totalCount": 1928
      },
      {
        "competitionCount": 12,
        "datasetCount": 76,
        "description": null,
        "displayName": "future prediction",
        "fontAwesomeIcon": null,
        "fullPath": "problem type > future prediction",
        "id": 14209,
        "isInherited": false,
        "listingUrl": "/competitions?sortBy=relevance&group=all&search=tag%3A%27future prediction%27",
        "name": "future prediction",
        "scriptCount": 119,
        "tagUrl": "/tags/future-prediction",
        "totalCount": 207
      }
    ],
    "type": "competition"
  },
  "competitionDescription": "Forecast future traffic to Wikipedia pages",
  "competitionId": 6768,
  "competitionName": "web-traffic-time-series-forecasting",
  "competitionTitle": "Web Traffic Time Series Forecasting",
  "competitionUrl": "/c/web-traffic-time-series-forecasting",
  "coverImageUrl": null,
  "deadline": "2017-11-15T23:59:00Z",
  "enabledDate": "2017-07-13T20:07:02.85Z",
  "evaluationMetric": "SMAPE",
  "hostSegment": "research",
  "hostSegmentTitle": "Research",
  "isInClass": false,
  "isKernelsSubmissionsOnly": false,
  "isLimited": false,
  "isOngoingCompetition": false,
  "isPrivate": false,
  "maxDailySubmissions": 5,
  "maxTeamSize": null,
  "medal": null,
  "mergerDeadline": "2017-09-05T23:59:00Z",
  "newEntrantDeadline": "2017-09-05T23:59:00Z",
  "organizationAvatarUrl": null,
  "organizationName": "Google",
  "organizationUrl": "google",
  "rewardDisplay": "$25,000",
  "rewardQuantity": 25000.0,
  "rewardTypeName": "USD",
  "submissionsDisabled": false,
  "thumbnailImageUrl": "https://storage.googleapis.com/kaggle-competitions/kaggle/6768/logos/thumb76_76.png",
  "totalKernels": 0,
  "totalTeams": 1095,
  "userHasEntered": false,
  "userRank": null,
  "userTeamUsers": []
}
