{
  "awardsPoints": true,
  "categories": {
    "categories": [
      {
        "competitionCount": 92,
        "datasetCount": 98,
        "description": null,
        "displayName": "tabular data",
        "fontAwesomeIcon": null,
        "fullPath": "data type > tabular data",
        "id": 14101,
        "isInherited": false,
        "listingUrl": "/competitions?sortBy=relevance&group=all&search=tag%3A%27tabular data%27",
        "name": "tabular data",
        "scriptCount": 115,
        "tagUrl": "/tags/tabular-data",
        "totalCount": 305
      },
      {
        "competitionCount": 4,
        "datasetCount": 1,
        "description": null,
        "displayName": "mathematical optimization",
        "fontAwesomeIcon": null,
        "fullPath": "problem type > mathematical optimization",
        "id": 14218,
        "isInherited": false,
        "listingUrl": "/competitions?sortBy=relevance&group=all&search=tag%3A%27mathematical optimization%27",
        "name": "mathematical optimization",
        "scriptCount": 4,
        "tagUrl": "/tags/mathematical-optimization",
        "totalCount": 9
      }
    ],
    "type": "competition"
  },
  "competitionDescription": "\u266b Alarm\u00a0bells ring, are you listening?\u00a0Santa's sleigh has gone\u00a0missing\u00a0\u266b",
  "competitionId": 4704,
  "competitionName": "santas-stolen-sleigh",
  "competitionTitle": "Santa's Stolen Sleigh",
  "competitionUrl": "/c/santas-stolen-sleigh",
  "coverImageUrl": null,
  "deadline": "2016-01-08T23:59:00Z",
  "enabledDate": "2015-12-01T00:50:16.923Z",
  "evaluationMetric": "SantaRideShare",
  "hostSegment": "featured",
  "hostSegmentTitle": "Featured",
  "isInClass": false,
  "isKernelsSubmissionsOnly": false,
  "isLimited": false,
  "isOngoingCompetition": false,
  "isPrivate": false,
  "maxDailySubmissions": 5,
  "maxTeamSize": null,
  "medal": null,
  "mergerDeadline": "2016-01-01T23:59:00Z",
  "newEntrantDeadline": "2016-01-01T23:59:00Z",
  "organizationAvatarUrl": null,
  "organizationName": null,
  "organizationUrl": null,
  "rewardDisplay": "$20,000",
  "rewardQuantity": 20000.0,
  "rewardTypeName": "USD",
  "submissionsDisabled": false,
  "thumbnailImageUrl": "https://storage.googleapis.com/kaggle-competitions/kaggle/4704/logos/thumb76_76.png",
  "totalKernels": 0,
  "totalTeams": 1127,
  "userHasEntered": false,
  "userRank": null,
  "userTeamUsers": []
}
