{
  "awardsPoints": true,
  "categories": {
    "categories": [
      {
        "competitionCount": 2,
        "datasetCount": 44,
        "description": null,
        "displayName": "object recognition",
        "fontAwesomeIcon": null,
        "fullPath": "problem type > object recognition",
        "id": 14217,
        "isInherited": false,
        "listingUrl": "/competitions?sortBy=relevance&group=all&search=tag%3A%27object recognition%27",
        "name": "object recognition",
        "scriptCount": 21,
        "tagUrl": "/tags/object-recognition",
        "totalCount": 67
      },
      {
        "competitionCount": 3,
        "datasetCount": 400,
        "description": "The automobile tag is everything about cars. Analyze insurance rates or how far you can go on one gallon of petrol.",
        "displayName": "automobiles",
        "fontAwesomeIcon": null,
        "fullPath": "technology and applied sciences > transport > automobiles",
        "id": 12402,
        "isInherited": false,
        "listingUrl": "/competitions?sortBy=relevance&group=all&search=tag%3A%27automobiles%27",
        "name": "automobiles",
        "scriptCount": 23,
        "tagUrl": "/tags/automobiles",
        "totalCount": 426
      },
      {
        "competitionCount": 70,
        "datasetCount": 705,
        "description": null,
        "displayName": "image data",
        "fontAwesomeIcon": null,
        "fullPath": "data type > image data",
        "id": 14102,
        "isInherited": false,
        "listingUrl": "/competitions?sortBy=relevance&group=all&search=tag%3A%27image data%27",
        "name": "image data",
        "scriptCount": 425,
        "tagUrl": "/tags/image-data",
        "totalCount": 1200
      }
    ],
    "type": "competition"
  },
  "competitionDescription": "Can computer vision spot distracted drivers?",
  "competitionId": 5048,
  "competitionName": "state-farm-distracted-driver-detection",
  "competitionTitle": "State Farm Distracted Driver Detection",
  "competitionUrl": "/c/state-farm-distracted-driver-detection",
  "coverImageUrl": null,
  "deadline": "2016-08-01T23:59:00Z",
  "enabledDate": "2016-04-05T17:06:37.883Z",
  "evaluationMetric": "Multiclass Loss",
  "hostSegment": "featured",
  "hostSegmentTitle": "Featured",
  "isInClass": false,
  "isKernelsSubmissionsOnly": false,
  "isLimited": false,
  "isOngoingCompetition": false,
  "isPrivate": false,
  "maxDailySubmissions": 5,
  "maxTeamSize": null,
  "medal": null,
  "mergerDeadline": "2016-07-25T23:59:00Z",
  "newEntrantDeadline": "2016-07-25T23:59:00Z",
  "organizationAvatarUrl": null,
  "organizationName": null,
  "organizationUrl": null,
  "rewardDisplay": "$65,000",
  "rewardQuantity": 65000.0,
  "rewardTypeName": "USD",
  "submissionsDisabled": false,
  "thumbnailImageUrl": "https://storage.googleapis.com/kaggle-competitions/kaggle/5048/logos/thumb76_76.png",
  "totalKernels": 0,
  "totalTeams": 1440,
  "userHasEntered": false,
  "userRank": null,
  "userTeamUsers": []
}